docspore/__init__.py
docspore-0.1.0.dist-info/licenses/LICENSE
docspore-0.1.0.dist-info/METADATA
docspore-0.1.0.dist-info/WHEEL
docspore-0.1.0.dist-info/top_level.txt
docspore-0.1.0.dist-info/RECORD
