Metadata-Version: 2.4
Name: docspore
Version: 0.1.0
Summary: TODO: Describe your project
Author-email: Chris Greening <chris@christophergreening.com>
Requires-Python: >=3.9
License-File: LICENSE
Dynamic: license-file
